fasttrader
tests
