Metadata-Version: 2.1
Name: fasttrader
Version: 0.4.0
Summary: Welcome to FastTrader, Your Gateway to Innovative Financial Analysis!
Home-page: https://github.com/CS594GROUP2/backtester
Author: CS594GROUP2
Author-email: <johnpiapian@gmail.com>
License: MIT
Keywords: python,yfinance,trading,backtesting,stock market,trading strategies
Classifier: Development Status :: 1 - Planning
Classifier: Intended Audience :: Financial and Insurance Industry
Classifier: Programming Language :: Python :: 3
Classifier: Operating System :: Unix
Classifier: Operating System :: MacOS :: MacOS X
Classifier: Operating System :: Microsoft :: Windows
License-File: LICENSE
